xy_request_handler_base/Base.py
xy_request_handler_base/IBase.py
xy_request_handler_base/WSBase.py
xy_request_handler_base/__init__.py
xy_request_handler_base-1.0.0.dist-info/LICENSE
xy_request_handler_base-1.0.0.dist-info/METADATA
xy_request_handler_base-1.0.0.dist-info/WHEEL
xy_request_handler_base-1.0.0.dist-info/top_level.txt
xy_request_handler_base-1.0.0.dist-info/RECORD
